centresurv/__innit__.py
centresurv/analyse.py
centresurv/maps.py
centresurv/postcode_setup.py
centresurv/setup.py
centresurv-0.1.2.dist-info/METADATA
centresurv-0.1.2.dist-info/WHEEL
centresurv-0.1.2.dist-info/entry_points.txt
centresurv-0.1.2.dist-info/license_files/LICENSE
centresurv-0.1.2.dist-info/RECORD
