Metadata-Version: 2.1
Name: centresurv
Version: 0.1.2
Summary: For assessment of service distribution in an area.
Project-URL: Homepage, https://gitlab.com/computational.oncology/geoserv
Classifier: License :: OSI Approved :: GNU General Public License v3 (GPLv3)
Classifier: Operating System :: OS Independent
Classifier: Programming Language :: Python :: 3
Requires-Python: >=3.6
